backpack/__init__.py
backpack/autoidentity.py
backpack/cwadapter.py
backpack/geometry.py
backpack/kvs.py
backpack/rtsp.py
backpack/skyline.py
backpack/timepiece.py
backpack/annotation/__init__.py
backpack/annotation/annotation.py
backpack/annotation/color.py
backpack/annotation/driver.py
backpack/annotation/opencv.py
backpack/annotation/panorama.py
backpack/config/__init__.py
backpack/config/config.py
backpack/config/geometry.py
backpack/config/serde.py
backpack/config/tool.py
panorama_backpack-0.3.2.dist-info/LICENSE
panorama_backpack-0.3.2.dist-info/METADATA
panorama_backpack-0.3.2.dist-info/WHEEL
panorama_backpack-0.3.2.dist-info/top_level.txt
panorama_backpack-0.3.2.dist-info/RECORD
