Metadata-Version: 2.1
Name: panorama-backpack
Version: 0.3.2
Summary: Tools for AWS Panorama development
Home-page: https://github.com/Neosperience/backpack
Download-URL: https://github.com/Neosperience/backpack/archive/refs/tags/v0.3.2.tar.gz
Author: Janos Tolgyesi
Author-email: janos.tolgyesi@neosperience.com
Keywords: aws,panorama,video-analysis
Classifier: Programming Language :: Python :: 3.7
Requires-Python: >=3.7
License-File: LICENSE
Requires-Dist: boto3 (~=1.26.102)
Requires-Dist: botocore (~=1.29.102)
Requires-Dist: jmespath (~=1.0.1)
Requires-Dist: numpy (~=1.21.6)
Requires-Dist: pydantic (~=1.10.7)
Requires-Dist: python-dateutil (~=2.8.2)
Requires-Dist: python-dotenv (~=0.21.1)
Requires-Dist: s3transfer (~=0.6.0)
Requires-Dist: six (~=1.9.0)
Requires-Dist: urllib3 (~=1.26.15)
Provides-Extra: opencv
Requires-Dist: opencv-headless ; extra == 'opencv'
